{
  "@context": "https://schema.org",
  "@type": "Organization",
  "name": "{{BUSINESS_NAME}}",
  "url": "{{BUSINESS_URL}}",
  "image": "{{BUSINESS_IMAGE}}",
  "telephone": "{{BUSINESS_PHONE}}",
  "email": "{{BUSINESS_EMAIL}}",
    "address": {
      "@type": "PostalAddress",
      "streetAddress": "{{BUSINESS_ADDRESS}}",
      "addressLocality": "{{BUSINESS_CITY}}",
       "postalCode": "{{BUSINESS_ZIP}}",
       "addressCountry": "{{BUSINESS_COUNTRY}}"
    },
    "hasMap":"{{BUSINESS_MAP}}",
    "openingHours":"Mo-Fri 9:00-19:00",
    "priceRange":"$ - $$$",
    "sameAs":[
    "{{BUSINESS_LINKEDIN}}",
    "{{BUSINESS_FACEBOOK}}",
    "{{BUSINESS_INSTAGRAM}}"
  ],
  "founder": [
    {
      "@type": "Person",
      "name": "Rati Abashmadze",
      "jobTitle": "Managing partner",
      "sameAs":"https://stage.pbservices.ge/about/rati-abashmadze/"
    }
  ],
  "employee": [
    {
      "@type": "Person",
      "name": "Sopho Chaduneli",
      "jobTitle": "Head of Consulting Team",
      "sameAs":"https://stage.pbservices.ge/ar/about/sofo-chaduneli/"
    },
    {
      "@type": "Person",
      "name": "Francesco Castronovo",
      "jobTitle": "Web Consultant",
      "sameAs":"https://fralenuvole.art"
    }
  ]
}